CompressedFisher/__init__.py
CompressedFisher/fisher.py
CompressedFisher/distributions/__init__.py
CompressedFisher/distributions/gaussian.py
CompressedFisher/distributions/poisson.py
CompressedFisher-0.1.0.dist-info/LICENSE
CompressedFisher-0.1.0.dist-info/METADATA
CompressedFisher-0.1.0.dist-info/WHEEL
CompressedFisher-0.1.0.dist-info/top_level.txt
CompressedFisher-0.1.0.dist-info/RECORD
