Metadata-Version: 2.1
Name: CompressedFisher
Version: 0.1.0
Summary: A Python package implementing the Compressed Fisher method of Coulton & Wandelt
Home-page: https://github.com/wcoulton/CompressedFisher
Author: Will Coulton
License: BSD 2-clause
Platform: UNKNOWN
Classifier: Development Status :: 1 - Planning
Classifier: Intended Audience :: Science/Research
Classifier: License :: OSI Approved :: BSD License
Classifier: Operating System :: POSIX :: Linux
Classifier: Programming Language :: Python :: 2
Classifier: Programming Language :: Python :: 2.7
Classifier: Programming Language :: Python :: 3
Classifier: Programming Language :: Python :: 3.4
Classifier: Programming Language :: Python :: 3.5
License-File: LICENSE
Requires-Dist: numpy
Requires-Dist: scipy
